MANS/__init__.py
MANS-0.1.dist-info/METADATA
MANS-0.1.dist-info/WHEEL
MANS-0.1.dist-info/top_level.txt
MANS-0.1.dist-info/RECORD
