Metadata-Version: 2.1
Name: MANS
Version: 0.1
Summary: Test for Uploading
Author: GOMAA
Author-email: M_Noma@yahoo.com
Classifier: Programming Language :: Python :: 3
Classifier: License :: OSI Approved :: MIT License
Classifier: Operating System :: OS Independent
